{
  "model": {
    "type": "minecraft:select",
    "cases": [
      {
        "type": "minecraft:model",
        "model": {
          "type": "minecraft:model",
          "model": "betterchristmaschests:item/oak_chest_boat"
        },
        "when": [
          "12-24",
          "12-25",
          "12-26"
        ]
      }
    ],
    "fallback": {
      "type": "minecraft:model",
      "model": "minecraft:item/oak_chest_boat"
    },
    "pattern": "MM-dd",
    "property": "minecraft:local_time"
  }
}